unidecode_replace/__init__.py
unidecode_replace/func.py
unidecode_replace/match.py
unidecode_replace/py.typed
unidecode_replace/replace.py
unidecode_replace/replicas.py
unidecode_replace/search_item.py
unidecode_replace/version.py
unidecode_replace-1.0.1.dist-info/METADATA
unidecode_replace-1.0.1.dist-info/WHEEL
unidecode_replace-1.0.1.dist-info/RECORD
