Metadata-Version: 2.1
Name: unidecode-replace
Version: 1.0.1
Summary: Python package providing search-and-replace in a unidecode compatible manner
Project-URL: Homepage, https://github.com/vsego/unidecode-replace
Project-URL: Bug Tracker, https://github.com/vsego/unidecode-replace/issues
Project-URL: Changelog, https://github.com/vsego/unidecode-replace/blob/master/CHANGELOG.md
Author-email: Vedran Sego <vsego@vsego.org>
License-Expression: MIT
Classifier: Operating System :: OS Independent
Classifier: Programming Language :: Python :: 3.10
Classifier: Programming Language :: Python :: 3.11
Classifier: Typing :: Typed
Requires-Python: >=3.10
Requires-Dist: unidecode
